gdshop_proto/auth_provider/auth_pb2.py
gdshop_proto/auth_provider/auth_pb2_grpc.py
gdshop_proto/auth_provider/profile_pb2.py
gdshop_proto/auth_provider/profile_pb2_grpc.py
gdshop_proto/db.py
gdshop_proto/event_bridge.py
gdshop_proto/settings.py
gdshop_proto/sms_provider/sms_pb2.py
gdshop_proto/sms_provider/sms_pb2_grpc.py
gdshop_proto-0.1.2.dist-info/METADATA
gdshop_proto-0.1.2.dist-info/WHEEL
gdshop_proto-0.1.2.dist-info/RECORD
